README.md
setup.py
ashares/__init__.py
ashares/cmd.py
ashares/daemon.py
ashares/db.py
ashares/init.py
ashares/local.py
ashares/log.py
ashares/remote.py
ashares/spliter.py
x_mroy_202.egg-info/PKG-INFO
x_mroy_202.egg-info/SOURCES.txt
x_mroy_202.egg-info/dependency_links.txt
x_mroy_202.egg-info/entry_points.txt
x_mroy_202.egg-info/not-zip-safe
x_mroy_202.egg-info/requires.txt
x_mroy_202.egg-info/top_level.txt