Metadata-Version: 1.0
Name: x-mroy-202
Version: 0.4.5
Summary: a data cache extend
Home-page: https://github.com/Qingluan/x-mroy-1.git
Author: Qing luan
Author-email: UNKNOWN
License: MIT
Platform: UNKNOWN
